[
  {
    "id": "5f5a82cd-7538-4ab6-ad3b-198caba50ddd",
    "data": [
      {
        "text": "theft",
        "meta": "@sys.ignore",
        "userDefined": false
      }
    ],
    "isTemplate": false,
    "count": 0,
    "updated": 0
  },
  {
    "id": "98fe1f16-9713-4b6c-885c-ad96b0ab06e1",
    "data": [
      {
        "text": "something is ",
        "userDefined": false
      },
      {
        "text": "missing",
        "meta": "@sys.ignore",
        "userDefined": false
      },
      {
        "text": " from my ",
        "userDefined": false
      },
      {
        "text": "vehicle",
        "meta": "@sys.ignore",
        "userDefined": false
      }
    ],
    "isTemplate": false,
    "count": 0,
    "updated": 0
  },
  {
    "id": "6b7c133b-aa29-455b-ba91-d017c2054151",
    "data": [
      {
        "text": "a part is ",
        "userDefined": false
      },
      {
        "text": "missing",
        "meta": "@sys.ignore",
        "userDefined": false
      }
    ],
    "isTemplate": false,
    "count": 0,
    "updated": 0
  },
  {
    "id": "6d7088d6-28d7-4d9a-b17e-39ccf9ab698a",
    "data": [
      {
        "text": "a part was ",
        "userDefined": false
      },
      {
        "text": "stolen",
        "meta": "@sys.ignore",
        "userDefined": false
      }
    ],
    "isTemplate": false,
    "count": 0,
    "updated": 0
  },
  {
    "id": "95959641-128b-4950-8447-080e62c8bfa1",
    "data": [
      {
        "text": "vehicle",
        "meta": "@sys.ignore",
        "userDefined": false
      },
      {
        "text": " was robbed",
        "userDefined": false
      }
    ],
    "isTemplate": false,
    "count": 0,
    "updated": 0
  },
  {
    "id": "91c21600-42e0-4ce0-b109-0614741c742a",
    "data": [
      {
        "text": "robbed",
        "userDefined": false
      }
    ],
    "isTemplate": false,
    "count": 0,
    "updated": 0
  },
  {
    "id": "5e6c1694-6ea9-4cdc-95a5-823311b6794d",
    "data": [
      {
        "text": "it was a ",
        "userDefined": false
      },
      {
        "text": "theft",
        "meta": "@sys.ignore",
        "userDefined": false
      }
    ],
    "isTemplate": false,
    "count": 0,
    "updated": 0
  },
  {
    "id": "786d4df3-0717-4eaf-b163-8433b4f2ada7",
    "data": [
      {
        "text": "there was a ",
        "userDefined": false
      },
      {
        "text": "theft",
        "meta": "@sys.ignore",
        "userDefined": false
      }
    ],
    "isTemplate": false,
    "count": 0,
    "updated": 0
  },
  {
    "id": "64b9896a-7ad0-4b37-8192-65cc0e94e70c",
    "data": [
      {
        "text": "thief",
        "meta": "@sys.ignore",
        "userDefined": false
      },
      {
        "text": " ",
        "userDefined": false
      },
      {
        "text": "stole",
        "meta": "@sys.ignore",
        "userDefined": false
      },
      {
        "text": " my ",
        "userDefined": false
      },
      {
        "text": "vehicle",
        "meta": "@sys.ignore",
        "userDefined": false
      }
    ],
    "isTemplate": false,
    "count": 0,
    "updated": 0
  },
  {
    "id": "9c77d14a-7d9d-406b-a1ed-a88b495b2d7e",
    "data": [
      {
        "text": "vehicle",
        "meta": "@sys.ignore",
        "userDefined": false
      },
      {
        "text": " got ",
        "userDefined": false
      },
      {
        "text": "stolen",
        "meta": "@sys.ignore",
        "userDefined": false
      }
    ],
    "isTemplate": false,
    "count": 0,
    "updated": 0
  }
]